eoq3tcp/__init__.py
eoq3tcp/tcpdomainclient/__init__.py
eoq3tcp/tcpdomainclient/tcpdomainclient.py
eoq3tcp/tcpdomainhost/__init__.py
eoq3tcp/tcpdomainhost/tcpdomainhost.py
eoq3tcp-2.9.3.dist-info/LICENSE
eoq3tcp-2.9.3.dist-info/METADATA
eoq3tcp-2.9.3.dist-info/WHEEL
eoq3tcp-2.9.3.dist-info/top_level.txt
eoq3tcp-2.9.3.dist-info/RECORD
