Metadata-Version: 2.2
Name: eoq3tcp
Version: 2.9.3
Summary: TCP domain client and host
Author-email: Bjoern Annighoefer <bjoern.annighoefer@ils.uni-stuttgart.de>
Project-URL: Homepage, https://gitlab.com/eoq/py/eoq3tcp
Project-URL: Issues, https://gitlab.com/eoq/py/eoq3tcp/-/issues
Classifier: Programming Language :: Python :: 3
Classifier: License :: OSI Approved :: MIT License
Classifier: Operating System :: OS Independent
Requires-Python: >=3.10
License-File: LICENSE
Requires-Dist: eoq3
